lidarr_youtube_downloader/lyd-unmapped.py
lidarr_youtube_downloader/lyd.py
lidarr_youtube_downloader/view/ffmpeg
lidarr_youtube_downloader/view/ffmpeg_result
lidarr_youtube_downloader/view/lidarr
lidarr_youtube_downloader/view/lidarrdb_update
lidarr_youtube_downloader/view/missing
lidarr_youtube_downloader/view/tagging
lidarr_youtube_downloader/view/youtube-search
lidarr_youtube_downloader/view/yt-dlp
lidarr_youtube_downloader/view/yt-dlp_result
lidarr_youtube_downloader-0.3.33.dist-info/LICENSE
lidarr_youtube_downloader-0.3.33.dist-info/METADATA
lidarr_youtube_downloader-0.3.33.dist-info/WHEEL
lidarr_youtube_downloader-0.3.33.dist-info/entry_points.txt
lidarr_youtube_downloader-0.3.33.dist-info/RECORD
