Metadata-Version: 2.3
Name: lidarr-youtube-downloader
Version: 0.3.33
Summary: 
Author: David O Neill
Author-email: dmz.oneill@gmail.com
Requires-Python: >=3.8,<4.0
Classifier: Programming Language :: Python :: 3
Classifier: Programming Language :: Python :: 3.8
Classifier: Programming Language :: Python :: 3.9
Classifier: Programming Language :: Python :: 3.10
Classifier: Programming Language :: Python :: 3.11
Classifier: Programming Language :: Python :: 3.12
Classifier: Programming Language :: Python :: 3.13
Requires-Dist: eyed3
Requires-Dist: requests
Requires-Dist: youtube-search-python
Project-URL: Repository, https://github.com/dmzoneill/lidarr-youtube-downloader
